setup.cfg
setup.py
case_frameworks/__init__.py
case_frameworks/cases.py
case_frameworks/mathematics.py
case_frameworks.egg-info/PKG-INFO
case_frameworks.egg-info/SOURCES.txt
case_frameworks.egg-info/dependency_links.txt
case_frameworks.egg-info/not-zip-safe
case_frameworks.egg-info/top_level.txt