Metadata-Version: 1.0
Name: case-frameworks
Version: 1.0.2060
Summary: Functions and Class for Consulting Preparation
Home-page: UNKNOWN
Author: UNKNOWN
Author-email: connormcdowall@gmail.com
License: UNKNOWN
Platform: UNKNOWN
